wikicodename/__init__.py
wikicodename/__main__.py
wikicodename/cache.py
wikicodename/config.py
wikicodename/generator.py
wikicodename/wiki_data.py
wikicodename/defaults/config/adjective.yaml
wikicodename/defaults/config/city.yaml
wikicodename/defaults/config/coctail.yaml
wikicodename/defaults/config/coffee.yaml
wikicodename/defaults/config/color.yaml
wikicodename/defaults/config/dinosaur.yaml
wikicodename/defaults/config/gwiazdozbior.yaml
wikicodename/defaults/config/main.yaml
wikicodename/defaults/config/women-scientist.yaml
wikicodename-1.0.1.dist-info/LICENSE
wikicodename-1.0.1.dist-info/METADATA
wikicodename-1.0.1.dist-info/WHEEL
wikicodename-1.0.1.dist-info/entry_points.txt
wikicodename-1.0.1.dist-info/top_level.txt
wikicodename-1.0.1.dist-info/RECORD
