Metadata-Version: 2.1
Name: wikicodename
Version: 1.0.1
Summary: Generate code names using lists and tables from Wikipedia articles.
Home-page: https://github.com/bartlomiej-zdrojewski/wikicodename
Author: Bartłomiej Zdrojewski
Author-email: bartlomiej.zdrojewski@gmail.com
License: MIT
Keywords: code name codename generate generator wiki Wikipedia
Platform: UNKNOWN
Classifier: Development Status :: 5 - Production/Stable
Classifier: Environment :: Console
Classifier: Intended Audience :: Developers
Classifier: License :: OSI Approved :: MIT License
Classifier: Natural Language :: English
Classifier: Operating System :: OS Independent
Classifier: Programming Language :: Python :: 3 :: Only
Classifier: Topic :: Utilities
Requires-Dist: PyYAML (<6.1,>=6.0)
Requires-Dist: appdirs (<1.5,>=1.4)
Requires-Dist: colorama (<0.5,>=0.4)
Requires-Dist: lxml (<4.8,>=4.7)
Requires-Dist: text-unidecode (<1.4,>=1.3)
